serve_swagger
