Metadata-Version: 2.1
Name: serve-swagger
Version: 1.3
Summary: serve swagger api docs locally fast
Home-page: https://github.com/joranbeasley/FlaskSwaggerAPIServer
Author: Joran Beasley
Author-email: joranbeasley@gmail.com
License: GPL
Platform: UNKNOWN
